bingefriend/shows/application/__init__.py
bingefriend/shows/application/config.py
bingefriend/shows/application/repositories/__init__.py
bingefriend/shows/application/repositories/database.py
bingefriend/shows/application/repositories/episode_repo.py
bingefriend/shows/application/repositories/genre_repo.py
bingefriend/shows/application/repositories/network_repo.py
bingefriend/shows/application/repositories/season_repo.py
bingefriend/shows/application/repositories/show_genre_repo.py
bingefriend/shows/application/repositories/show_repo.py
bingefriend/shows/application/repositories/web_channel_repo.py
bingefriend/shows/application/services/__init__.py
bingefriend/shows/application/services/episode_service.py
bingefriend/shows/application/services/genre_service.py
bingefriend/shows/application/services/network_service.py
bingefriend/shows/application/services/season_service.py
bingefriend/shows/application/services/show_genre_service.py
bingefriend/shows/application/services/show_service.py
bingefriend/shows/application/services/web_channel_service.py
bingefriend_shows_application-0.1.17.dist-info/LICENSE
bingefriend_shows_application-0.1.17.dist-info/METADATA
bingefriend_shows_application-0.1.17.dist-info/WHEEL
bingefriend_shows_application-0.1.17.dist-info/RECORD
