Metadata-Version: 2.3
Name: bingefriend-shows-application
Version: 0.1.17
Summary: 
Author: Tom Boone
Author-email: tbc@tomboone.com
Requires-Python: >=3.11
Classifier: Programming Language :: Python :: 3
Classifier: Programming Language :: Python :: 3.11
Classifier: Programming Language :: Python :: 3.12
Classifier: Programming Language :: Python :: 3.13
Requires-Dist: bingefriend-shows-client_tvmaze (>=0.1.2,<0.2.0)
Requires-Dist: bingefriend-shows-core (>=0.2.6,<0.3.0)
Requires-Dist: sqlalchemy (>=2.0.40,<3.0.0)
